Metadata-Version: 2.1
Name: PythonDynamicDoc
Version: 0.1.2
Summary: Uma biblioteca para manipulação dinâmica de documentos docx.
Home-page: https://github.com/SamuelSGSouza/Dynamic-Docs
Author: Samuel Santos
Author-email: samuels.g.desouza@gmail.com
Classifier: Programming Language :: Python :: 3
Classifier: License :: OSI Approved :: MIT License
Classifier: Operating System :: OS Independent
Requires-Python: >=3.6
License-File: LICENSE.txt
